zhijiang/__init__.py
zhijiang/zhijiang.7z
env_setup-0.1.1.dist-info/LICENSE.txt
env_setup-0.1.1.dist-info/METADATA
env_setup-0.1.1.dist-info/WHEEL
env_setup-0.1.1.dist-info/entry_points.txt
env_setup-0.1.1.dist-info/top_level.txt
env_setup-0.1.1.dist-info/RECORD
