Metadata-Version: 2.1
Name: env-setup
Version: 0.1.1
Summary: setup linux env, such as bashrc etc.
Home-page: https://github.com/xu-zhijiang/env-setup.git
Author: Xu Zhijiang
Author-email: 15852939122@163.com
Project-URL: Funding, https://github.com/xu-zhijiang
Project-URL: Source, https://github.com/xu-zhijiang/env-setup.git
Keywords: env setup,development,zhijiang
Classifier: Intended Audience :: Developers
Classifier: License :: OSI Approved :: MIT License
Requires-Python: >=2
License-File: LICENSE.txt
Requires-Dist: termcolor
Requires-Dist: fire
Provides-Extra: dev
Requires-Dist: check-manifest ; extra == 'dev'
Provides-Extra: test
Requires-Dist: coverage ; extra == 'test'
